None/__init__.py
jadecobra/__init__.py
jadecobra/aws_environment.py
jadecobra/cloudformation_deployer.py
jadecobra/setup_tdd.py
jadecobra/tester.py
jadecobra/toolkit.py
jadecobra/versioning.py
jadecobra/aws_lambda/__init__.py
jadecobra/aws_lambda/deploy/__init__.py
jadecobra/aws_lambda/deploy/deploy.py
jadecobra/aws_lambda/deploy/deploy_lambda.py
jadecobra/aws_lambda/deploy/lambda_function.py
jadecobra/aws_lambda/deploy/lambda_layer.py
jadecobra-0.3.76.dist-info/LICENSE
jadecobra-0.3.76.dist-info/METADATA
jadecobra-0.3.76.dist-info/WHEEL
jadecobra-0.3.76.dist-info/top_level.txt
jadecobra-0.3.76.dist-info/RECORD
