Metadata-Version: 2.1
Name: jadecobra
Version: 0.3.76
Summary: DRY
Author-email: johnnyblase <johnnyblasin@gmail.com>
License: MIT License
Project-URL: Homepage, https://github.com/jadecobra/jadecobra
Project-URL: Bug Tracker, https://github.com/jadecobra/jadecobra/issues
Classifier: Programming Language :: Python :: 3
Classifier: License :: OSI Approved :: MIT License
Classifier: Operating System :: OS Independent
Requires-Python: >=3.6
License-File: LICENSE
Requires-Dist: boto3
Requires-Dist: sniffer
